README
setup.py
src/django_xsendfile.egg-info/PKG-INFO
src/django_xsendfile.egg-info/SOURCES.txt
src/django_xsendfile.egg-info/dependency_links.txt
src/django_xsendfile.egg-info/requires.txt
src/django_xsendfile.egg-info/top_level.txt
src/xsendfile/__init__.py
src/xsendfile/models.py
src/xsendfile/settings.py
src/xsendfile/tests.py
src/xsendfile/testsettings.py
src/xsendfile/urls.py
src/xsendfile/views.py
src/xsendfile/widgets.py