Metadata-Version: 1.0
Name: django-xsendfile
Version: 1.0
Summary: A Django application to serve files using xsendfile
Home-page: http://toolpart.hu/code/download/django-xsendfile/
Author: ToolPart Team LLC
Author-email: toolpart@toolpart.hu
License: BSD
Platform: UNKNOWN
Classifier: Development Status :: 4 - Beta
Classifier: Framework :: Django
Classifier: Intended Audience :: Developers
Classifier: License :: OSI Approved :: BSD License
Classifier: Operating System :: OS Independent
Classifier: Programming Language :: Python
Classifier: Topic :: Internet :: WWW/HTTP
